[
  {
    "name": "cb128_ld16_cc0.25",
    "latent_dim": 16,
    "codebook_size": 128,
    "commitment_cost": 0.25,
    "mse": 0.23809757828712463,
    "bandwidth": 7,
    "codebook_usage": 0.1015625
  },
  {
    "name": "cb128_ld2_cc0.25",
    "latent_dim": 2,
    "codebook_size": 128,
    "commitment_cost": 0.25,
    "mse": 0.1836567223072052,
    "bandwidth": 7,
    "codebook_usage": 1.0
  },
  {
    "name": "cb128_ld4_cc0.01",
    "latent_dim": 4,
    "codebook_size": 128,
    "commitment_cost": 0.01,
    "mse": 0.16441121697425842,
    "bandwidth": 7,
    "codebook_usage": 1.0
  },
  {
    "name": "cb128_ld4_cc0.05",
    "latent_dim": 4,
    "codebook_size": 128,
    "commitment_cost": 0.05,
    "mse": 0.1616504192352295,
    "bandwidth": 7,
    "codebook_usage": 1.0
  },
  {
    "name": "cb128_ld4_cc0.1",
    "latent_dim": 4,
    "codebook_size": 128,
    "commitment_cost": 0.1,
    "mse": 0.20493821799755096,
    "bandwidth": 7,
    "codebook_usage": 0.375
  },
  {
    "name": "cb128_ld4_cc0.25",
    "latent_dim": 4,
    "codebook_size": 128,
    "commitment_cost": 0.25,
    "mse": 0.17885172367095947,
    "bandwidth": 7,
    "codebook_usage": 1.0
  },
  {
    "name": "cb128_ld4_cc0.5",
    "latent_dim": 4,
    "codebook_size": 128,
    "commitment_cost": 0.5,
    "mse": 0.1982881724834442,
    "bandwidth": 7,
    "codebook_usage": 0.484375
  },
  {
    "name": "cb128_ld4_cc1.0",
    "latent_dim": 4,
    "codebook_size": 128,
    "commitment_cost": 1.0,
    "mse": 0.19727157056331635,
    "bandwidth": 7,
    "codebook_usage": 0.5390625
  },
  {
    "name": "cb128_ld4_cc2.0",
    "latent_dim": 4,
    "codebook_size": 128,
    "commitment_cost": 2.0,
    "mse": 0.20243987441062927,
    "bandwidth": 7,
    "codebook_usage": 0.390625
  },
  {
    "name": "cb128_ld4_cc5.0",
    "latent_dim": 4,
    "codebook_size": 128,
    "commitment_cost": 5.0,
    "mse": 0.5455169081687927,
    "bandwidth": 7,
    "codebook_usage": 0.0078125
  },
  {
    "name": "cb128_ld8_cc0.25",
    "latent_dim": 8,
    "codebook_size": 128,
    "commitment_cost": 0.25,
    "mse": 0.21686595678329468,
    "bandwidth": 7,
    "codebook_usage": 0.1875
  },
  {
    "name": "cb256_ld16_cc0.25",
    "latent_dim": 16,
    "codebook_size": 256,
    "commitment_cost": 0.25,
    "mse": 0.2311425358057022,
    "bandwidth": 8,
    "codebook_usage": 0.05859375
  },
  {
    "name": "cb256_ld2_cc0.25",
    "latent_dim": 2,
    "codebook_size": 256,
    "commitment_cost": 0.25,
    "mse": 0.17624607682228088,
    "bandwidth": 8,
    "codebook_usage": 1.0
  },
  {
    "name": "cb256_ld4_cc0.25",
    "latent_dim": 4,
    "codebook_size": 256,
    "commitment_cost": 0.25,
    "mse": 0.19802099466323853,
    "bandwidth": 8,
    "codebook_usage": 0.28515625
  },
  {
    "name": "cb256_ld8_cc0.25",
    "latent_dim": 8,
    "codebook_size": 256,
    "commitment_cost": 0.25,
    "mse": 0.21094904839992523,
    "bandwidth": 8,
    "codebook_usage": 0.1171875
  },
  {
    "name": "cb32_ld16_cc0.25",
    "latent_dim": 16,
    "codebook_size": 32,
    "commitment_cost": 0.25,
    "mse": 0.35431969165802,
    "bandwidth": 5,
    "codebook_usage": 0.125
  },
  {
    "name": "cb32_ld2_cc0.25",
    "latent_dim": 2,
    "codebook_size": 32,
    "commitment_cost": 0.25,
    "mse": 0.2097499519586563,
    "bandwidth": 5,
    "codebook_usage": 1.0
  },
  {
    "name": "cb32_ld4_cc0.25",
    "latent_dim": 4,
    "codebook_size": 32,
    "commitment_cost": 0.25,
    "mse": 0.21590004861354828,
    "bandwidth": 5,
    "codebook_usage": 0.75
  },
  {
    "name": "cb32_ld8_cc0.25",
    "latent_dim": 8,
    "codebook_size": 32,
    "commitment_cost": 0.25,
    "mse": 0.23874080181121826,
    "bandwidth": 5,
    "codebook_usage": 0.4375
  },
  {
    "name": "cb512_ld16_cc0.25",
    "latent_dim": 16,
    "codebook_size": 512,
    "commitment_cost": 0.25,
    "mse": 0.23294980823993683,
    "bandwidth": 9,
    "codebook_usage": 0.02734375
  },
  {
    "name": "cb512_ld4_cc0.25",
    "latent_dim": 4,
    "codebook_size": 512,
    "commitment_cost": 0.25,
    "mse": 0.12827540934085846,
    "bandwidth": 9,
    "codebook_usage": 1.0
  },
  {
    "name": "cb512_ld8_cc0.25",
    "latent_dim": 8,
    "codebook_size": 512,
    "commitment_cost": 0.25,
    "mse": 0.20616942644119263,
    "bandwidth": 9,
    "codebook_usage": 0.07421875
  },
  {
    "name": "cb64_ld16_cc0.25",
    "latent_dim": 16,
    "codebook_size": 64,
    "commitment_cost": 0.25,
    "mse": 0.24565653502941132,
    "bandwidth": 6,
    "codebook_usage": 0.171875
  },
  {
    "name": "cb64_ld2_cc0.25",
    "latent_dim": 2,
    "codebook_size": 64,
    "commitment_cost": 0.25,
    "mse": 0.1968267410993576,
    "bandwidth": 6,
    "codebook_usage": 1.0
  },
  {
    "name": "cb64_ld4_cc0.25",
    "latent_dim": 4,
    "codebook_size": 64,
    "commitment_cost": 0.25,
    "mse": 0.20830558240413666,
    "bandwidth": 6,
    "codebook_usage": 0.515625
  },
  {
    "name": "cb64_ld8_cc0.25",
    "latent_dim": 8,
    "codebook_size": 64,
    "commitment_cost": 0.25,
    "mse": 0.2332448810338974,
    "bandwidth": 6,
    "codebook_usage": 0.21875
  },
  {
    "name": "cb512_ld2_cc0.25",
    "latent_dim": 2,
    "codebook_size": 512,
    "commitment_cost": 0.25,
    "mse": 0.1707,
    "bandwidth": 9,
    "codebook_usage": 0.9922
  }
]